tpysui/__init__.py
tpysui/tpysui.py
tpysui/version.py
tpysui/modals/__init__.py
tpysui/modals/configfm.py
tpysui/modals/confirm.py
tpysui/modals/pyconfig_add.py
tpysui/modals/pyconfig_new.py
tpysui/modals/pyconfig_popup.py
tpysui/modals/single_choice.py
tpysui/screens/__init__.py
tpysui/screens/configs.py
tpysui/screens/sui_config.py
tpysui/utils/__init__.py
tpysui/utils/genpy.py
tpysui/widgets/__init__.py
tpysui/widgets/editable_table.py
tpysui/widgets/simple_header.py
tpysui-0.4.1.dist-info/licenses/LICENSE
tpysui-0.4.1.dist-info/METADATA
tpysui-0.4.1.dist-info/WHEEL
tpysui-0.4.1.dist-info/entry_points.txt
tpysui-0.4.1.dist-info/top_level.txt
tpysui-0.4.1.dist-info/RECORD
