Metadata-Version: 2.4
Name: tpysui
Version: 0.4.1
Summary: Pysui and Configuration Editors
License-Expression: Apache-2.0
Project-URL: changelog, https://github.com/suitters/tpysui/blob/main/CHANGELOG.md
Project-URL: repository, https://github.com/suitters/tpysui
Project-URL: issues, https://github.com/suitters/tpysui/issues
Project-URL: documentation, https://github.com/suitters/tpysui/blob/main/docs/tpysui.rst
Keywords: pysui,editor,configuration,software development kit,sui,blockchain
Classifier: Development Status :: 4 - Beta
Classifier: Programming Language :: Python
Classifier: Programming Language :: Python :: 3.10
Classifier: Programming Language :: Python :: 3.11
Classifier: Programming Language :: Python :: 3.12
Classifier: Programming Language :: Python :: 3.13
Classifier: Programming Language :: Python :: Implementation :: CPython
Classifier: Programming Language :: Python :: Implementation :: PyPy
Requires-Python: >=3.10.6
License-File: LICENSE
Requires-Dist: textual<6.0.0,>=5.1.1
Requires-Dist: pysui<0.95.0,>=0.91.0
Requires-Dist: pathvalidate<4.0.0,>=3.3.1
Dynamic: license-file
